LICENSE.txt
README.rst
__init__.py
externalImports.py
omfit.py
omfit_gui.py
omfit_halt.py
omfit_parse_args.py
omfit_plot.py
omfit_setup.py
omfit_tree.py
setup.py
utils.py
utils_tk.py
utils_widgets.py
version
classes/__init__.py
extras/__init__.py
extras/graphics/LOM.png
extras/graphics/OMFIT_font.bf
extras/graphics/OMFIT_font.ttf
extras/graphics/OMFIT_logo.gif
extras/graphics/OMFIT_logo.pdf
extras/graphics/OMFIT_logo_color.gif
extras/graphics/OMFIT_logo_color.pdf
extras/graphics/OMFIT_logo_olympics.gif
extras/graphics/OMFIT_logo_olympics.pdf
extras/graphics/__init__.py
extras/graphics/autoX.ppm
extras/graphics/autoY.ppm
extras/graphics/bookmark.ppm
extras/graphics/colors.py
extras/graphics/copy.ppm
extras/graphics/crosshair.ppm
extras/graphics/error.gif
extras/graphics/events.py
extras/graphics/fonts.py
extras/graphics/help.ppm
extras/graphics/info.gif
extras/graphics/legend.ppm
extras/graphics/linked.ppm
extras/graphics/mail.ppm
extras/graphics/matplotlib_backends.py
extras/graphics/paste.ppm
extras/graphics/pdf.ppm
extras/graphics/pin.ppm
extras/graphics/question.gif
extras/graphics/select.ppm
extras/graphics/settings.ppm
extras/graphics/storage.ppm
extras/graphics/text.ppm
extras/graphics/trash.ppm
extras/graphics/unlinked.ppm
extras/graphics/warning.gif
extras/graphics/fonts/Humor-Sans.ttf
extras/graphics/fonts/Muli-Bold.ttf
extras/graphics/fonts/Muli-BoldItalic.ttf
extras/graphics/fonts/Muli-ExtraLight.ttf
extras/graphics/fonts/Muli-ExtraLightItalic.ttf
extras/graphics/fonts/Muli-Italic.ttf
extras/graphics/fonts/Muli-Light.ttf
extras/graphics/fonts/Muli-LightItalic.ttf
extras/graphics/fonts/Muli-Semi-BoldItalic.ttf
extras/graphics/fonts/Muli-SemiBold.ttf
extras/graphics/fonts/Muli.ttf
extras/graphics/themes/pkgIndex.tcl
extras/graphics/themes/aquativo/CreateImageLib.def
extras/graphics/themes/aquativo/ImageLib.tcl
extras/graphics/themes/aquativo/LICENSE
extras/graphics/themes/aquativo/aquativo.tcl
extras/graphics/themes/aquativo/images.tgz
omfit_classes.egg-info/PKG-INFO
omfit_classes.egg-info/SOURCES.txt
omfit_classes.egg-info/dependency_links.txt
omfit_classes.egg-info/top_level.txt
