Metadata-Version: 2.1
Name: omfit-classes
Version: 3.2026.4.2
Summary: Classes of OMFIT (One Modeling Framework For Integrated Tasks)
Home-page: https://omfit.io
Author: OMFIT developers
Author-email: meneghini@fusion.gat.com
License: MIT
Keywords: integrated modeling plasma framework
Platform: UNKNOWN
Classifier: Programming Language :: Python :: 3
Classifier: Operating System :: OS Independent
Classifier: License :: OSI Approved :: MIT License
License-File: LICENSE.txt
